kada_ge_store_plugin/__init__.py
kada_ge_store_plugin/kada_store_validation.py
kada_ge_store_plugin/data_docs_templates/bootstrap_table.j2
kada_ge_store_plugin/data_docs_templates/favicon.j2
kada_ge_store_plugin/data_docs_templates/index_page.j2
kada_ge_store_plugin/data_docs_templates/page.j2
kada_ge_store_plugin/data_docs_templates/section.j2
kada_ge_store_plugin/data_docs_templates/sidebar.j2
kada_ge_store_plugin/data_docs_templates/table.j2
kada_ge_store_plugin/data_docs_templates/top_navbar.j2
kada_ge_store_plugin/kada_gx_plugins/__init__.py
kada_ge_store_plugin/kada_gx_plugins/kada_pandas_datasource.py
kada_ge_store_plugin/kada_gx_plugins/kada_sql_query_asset.py
kada_ge_store_plugin/kada_gx_plugins/kada_adapters/__init__.py
kada_ge_store_plugin/kada_gx_plugins/kada_adapters/base.py
kada_ge_store_plugin/kada_gx_plugins/kada_adapters/snowflake_adapter.py
kada_ge_store_plugin/kada_gx_plugins/kada_adapters/utils.py
kada_ge_store_plugin/static/css/all.min.css
kada_ge_store_plugin/static/css/bootstrap-datepicker.min.css
kada_ge_store_plugin/static/css/bootstrap-table-filter-control.min.css
kada_ge_store_plugin/static/css/bootstrap-table.min.css
kada_ge_store_plugin/static/css/bootstrap.min.css
kada_ge_store_plugin/static/images/KADA_logo.svg
kada_ge_store_plugin/static/js/bootstrap-datepicker.min.js
kada_ge_store_plugin/static/js/bootstrap-table-filter-control.min.js
kada_ge_store_plugin/static/js/bootstrap-table.min.js
kada_ge_store_plugin/static/js/bootstrap.min.js
kada_ge_store_plugin/static/js/jquery-3.4.1.min.js
kada_ge_store_plugin/static/js/popper.min.js
kada_ge_store_plugin/static/webfonts/fa-brands-400.ttf
kada_ge_store_plugin/static/webfonts/fa-brands-400.woff2
kada_ge_store_plugin/static/webfonts/fa-regular-400.ttf
kada_ge_store_plugin/static/webfonts/fa-regular-400.woff2
kada_ge_store_plugin/static/webfonts/fa-solid-900.ttf
kada_ge_store_plugin/static/webfonts/fa-solid-900.woff2
kada_ge_store_plugin/static/webfonts/fa-v4compatibility.ttf
kada_gx_plugin-2.0.18.dist-info/licenses/LICENSE
kada_gx_plugin-2.0.18.dist-info/METADATA
kada_gx_plugin-2.0.18.dist-info/WHEEL
kada_gx_plugin-2.0.18.dist-info/top_level.txt
kada_gx_plugin-2.0.18.dist-info/RECORD
