Metadata-Version: 2.4
Name: kada-gx-plugin
Version: 2.0.18
Summary: kada-gx-plugin generates validation results in a format for loading into the K Platform.
Author-email: kada <contact@kada.ai>
Maintainer-email: kada <contact@kada.ai>
Project-URL: Homepage, https://kada.ai
Classifier: Development Status :: 5 - Production/Stable
Classifier: Programming Language :: Python :: 3.8
Classifier: Programming Language :: Python :: 3.9
Classifier: Programming Language :: Python :: 3.10
Classifier: Programming Language :: Python :: 3.11
Classifier: License :: OSI Approved :: Apache Software License
Classifier: Operating System :: OS Independent
Requires-Python: <4.0,>=3.8
License-File: LICENSE
Requires-Dist: great-expectations<=1.4.3,>=1.3.0
Provides-Extra: azure
Requires-Dist: azure-identity>=1.12.0; extra == "azure"
Requires-Dist: azure-storage-blob>=12.14.1; extra == "azure"
Provides-Extra: snowflake
Requires-Dist: snowflake-connector-python<3.15.0,>=3.13.0; extra == "snowflake"
Dynamic: license-file
